Metadata-Version: 1.2
Name: betfair-scraper
Version: 1.0
Summary: Betfair website scraper library
Home-page: https://github.com/meister245/betfair-scraper
Author: Zsolt Mester
Author-email: 
License: MIT
Project-URL: Code, https://github.com/meister245/betfair-scraper
Project-URL: Issue tracker, https://github.com/meister245/betfair-scraper/issues
Platform: UNKNOWN
Requires-Python: >=3.8
